fastdub/__init__.py
fastdub/__main__.py
fastdub/audio.py
fastdub/dubber.py
fastdub/ffmpeg_wrapper.py
fastdub/subtitles.py
fastdub/voicer.py
fastdub/translator/__init__.py
fastdub/translator/subs_translate.py
fastdub/utils/__init__.py
fastdub/utils/json2srt.py
fastdub/youtube/__init__.py
fastdub/youtube/downloader.py
fastdub/youtube/subtitles.py
fastdub/youtube/pafy/__init__.py
fastdub/youtube/pafy/backend_internal.py
fastdub/youtube/pafy/backend_shared.py
fastdub/youtube/pafy/backend_youtube_dl.py
fastdub/youtube/pafy/channel.py
fastdub/youtube/pafy/g.py
fastdub/youtube/pafy/jsinterp.py
fastdub/youtube/pafy/pafy.py
fastdub/youtube/pafy/playlist.py
fastdub/youtube/pafy/util.py
fastdub/youtube/yt_upload/__init__.py
fastdub/youtube/yt_upload/upload_video.py
fastdub/youtube/yt_upload/uploader.py
PyFastDub-3.1.3.dist-info/METADATA
PyFastDub-3.1.3.dist-info/WHEEL
PyFastDub-3.1.3.dist-info/top_level.txt
PyFastDub-3.1.3.dist-info/RECORD
