Metadata-Version: 2.1
Name: PyFastDub
Version: 3.1.3
Summary: A Python CLI package for voice over subtitles, with the ability to embed in video, audio ducking, and dynamic voice changer for a single track; auto translating; download and upload to YouTube supports
Author: Nikita (NIKDISSV)
Author-email: nikdissv@proton.me
License: MIT
Project-URL: Current Link, https://pypi.org/project/FastDub/
Project-URL: Download Voices, https://rhvoice.su/voices/
Project-URL: GitHub, https://github.com/NIKDISSV-Forever/FastDub/
Project-URL: YouTube, https://www.youtube.com/channel/UC8JV3zPSVm9EKSWD1XdkQvw/
Keywords: dubbing,voicing,fastdub,JustDub,SpeedDub,offline,free,easiest,subtitles,videos,veed,fast
Platform: UNKNOWN
Classifier: Development Status :: 5 - Production/Stable
Classifier: Environment :: Console
Classifier: Intended Audience :: Developers
Classifier: Intended Audience :: End Users/Desktop
Classifier: Intended Audience :: Other Audience
Classifier: Intended Audience :: Science/Research
Classifier: Intended Audience :: Telecommunications Industry
Classifier: License :: OSI Approved
Classifier: License :: OSI Approved :: MIT License
Classifier: Operating System :: OS Independent
Classifier: Natural Language :: English
Classifier: Natural Language :: Russian
Classifier: Programming Language :: Python :: 3
Classifier: Programming Language :: Python :: 3 :: Only
Classifier: Programming Language :: Python :: 3.8
Classifier: Programming Language :: Python :: 3.9
Classifier: Programming Language :: Python :: 3.10
Classifier: Programming Language :: Python :: 3.11
Classifier: Programming Language :: Python :: Implementation :: CPython
Classifier: Topic :: Multimedia
Classifier: Topic :: Multimedia :: Sound/Audio
Classifier: Topic :: Multimedia :: Sound/Audio :: Analysis
Classifier: Topic :: Multimedia :: Sound/Audio :: Conversion
Classifier: Topic :: Multimedia :: Sound/Audio :: Speech
Classifier: Topic :: Multimedia :: Video
Classifier: Topic :: Multimedia :: Video :: Conversion
Classifier: Topic :: Software Development :: Internationalization
Classifier: Topic :: Utilities
Classifier: Typing :: Typed
Requires-Python: >=3.8
Requires-Dist: moviepy
Requires-Dist: pyttsx3
Requires-Dist: pydub
Requires-Dist: imageio-ffmpeg
Requires-Dist: rich
Provides-Extra: all
Requires-Dist: moviepy ; extra == 'all'
Requires-Dist: pyttsx3 ; extra == 'all'
Requires-Dist: pydub ; extra == 'all'
Requires-Dist: imageio-ffmpeg ; extra == 'all'
Requires-Dist: rich ; extra == 'all'
Requires-Dist: translators ; extra == 'all'
Requires-Dist: download-youtube-subtitle ; extra == 'all'
Requires-Dist: youtube-search-python ; extra == 'all'
Requires-Dist: youtube-dl ; extra == 'all'
Requires-Dist: google-api-python-client ; extra == 'all'
Requires-Dist: oauth2client ; extra == 'all'
Provides-Extra: tr
Requires-Dist: translators ; extra == 'tr'
Provides-Extra: yt
Requires-Dist: download-youtube-subtitle ; extra == 'yt'
Requires-Dist: youtube-search-python ; extra == 'yt'
Requires-Dist: youtube-dl ; extra == 'yt'
Provides-Extra: ytu
Requires-Dist: google-api-python-client ; extra == 'ytu'
Requires-Dist: oauth2client ; extra == 'ytu'
